CreaTeBME/ImuSensor.py
CreaTeBME/SensorEmulator.py
CreaTeBME/SensorManager.py
CreaTeBME/__init__.py
CreaTeBME/connect.py
CreaTeBME/uuids.py
CreaTeBME-1.2.3.dist-info/LICENSE
CreaTeBME-1.2.3.dist-info/METADATA
CreaTeBME-1.2.3.dist-info/WHEEL
CreaTeBME-1.2.3.dist-info/top_level.txt
CreaTeBME-1.2.3.dist-info/RECORD
