Metadata-Version: 2.1
Name: CreaTeBME
Version: 1.2.3
Summary: Python Package for interfacing the bluetooth IMU module for CreaTe M8 BME.
Home-page: https://github.com/CreaTe-M8-BME/CreaTeBME
Author: Jonathan Matarazzi
Author-email: git@jonathanm.nl
Project-URL: Bug Tracker, https://github.com/CreaTe-M8-BME/CreaTeBME/issues
Classifier: Programming Language :: Python :: 3
Classifier: License :: OSI Approved :: GNU General Public License v3 (GPLv3)
Classifier: Operating System :: OS Independent
Requires-Python: >=3.7
License-File: LICENSE
Requires-Dist: bleak >=0.22.1
